[
    {
      "id": 1,
      "nome": "Bolo de Chocolate",
      "preco": "25.50",
      "imagem": "@/assets/images/luaDeMel.jpg",
      "quantidade": 5
    },
    {
      "id": 2,
      "nome": "Sonho",
      "preco": "25.50",
      "imagem": "@/assets/images/sonho.jpg",
      "quantidade": 10
    },
    {
      "id": 3,
      "nome": "Donuts",
      "preco": "25.50",
      "imagem": "@/assets/images/donuts.jpg",
      "quantidade": 3
    },
    {
      "id": 4,
      "nome": "Bolo de Morango",
      "preco": "30.00",
      "imagem": "@/assets/images/boloDeMorango.jpg",
      "quantidade": 2
    },
    {
      "id": 5,
      "nome": "Pudim",
      "preco": "18.00",
      "imagem": "@/assets/images/pudim.jpg",
      "quantidade": 7
    },
    {
      "id": 6,
      "nome": "Torta de Limão",
      "preco": "20.00",
      "imagem": "@/assets/images/tortaDeLimao.jpg",
      "quantidade": 4
    },
    {
      "id": 7,
      "nome": "Bolo de Cenoura",
      "preco": "22.00",
      "imagem": "@/assets/images/boloDeCenoura.jpg",
      "quantidade": 6
    },
    {
      "id": 8,
      "nome": "Churros",
      "preco": "15.00",
      "imagem": "@/assets/images/churros.jpg",
      "quantidade": 8
    },
    {
      "id": 9,
      "nome": "Torta de Maçã",
      "preco": "18.50",
      "imagem": "@/assets/images/tortaDeMaca.jpg",
      "quantidade": 3
    },
    {
      "id": 10,
      "nome": "Queijadinha",
      "preco": "12.50",
      "imagem": "@/assets/images/queijadinha.jpg",
      "quantidade": 9
    }
  ]
  